{
	"name": "ds_srs",
	"properties": {
		"linkedServiceName": {
			"referenceName": "ls_adlsg2",
			"type": "LinkedServiceReference"
		},
		"annotations": [],
		"type": "DelimitedText",
		"typeProperties": {
			"location": {
				"type": "AzureBlobFSLocation",
				"fileName": "User_Input.csv",
				"folderPath": "input",
				"fileSystem": "storage"
			},
			"columnDelimiter": ",",
			"escapeChar": "\\",
			"quoteChar": "\""
		},
		"schema": [
			{
				"type": "String"
			},
			{
				"type": "String"
			}
		]
	}
}